cubemap2pano/__init__.py
cubemap2pano/c2e.py
cubemap2pano/e2c.py
cubemap2pano-0.0.5.dist-info/METADATA
cubemap2pano-0.0.5.dist-info/WHEEL
cubemap2pano-0.0.5.dist-info/top_level.txt
cubemap2pano-0.0.5.dist-info/RECORD
