Metadata-Version: 2.4
Name: cubemap2pano
Version: 0.0.5
Summary: Convert cubemap to equirectangular panorama image and vice versa.
Author-email: serpong <tykim@xrleader.co.kr>
License-Expression: MIT
Project-URL: Homepage, https://github.com/xrleader/cubemap2pano
Keywords: panorama,cubemap,equirectangular,image,360,vr
Classifier: Programming Language :: Python :: 3.9
Classifier: Programming Language :: Python :: 3.10
Classifier: Programming Language :: Python :: 3.11
Classifier: Programming Language :: Python :: 3.12
Classifier: Operating System :: OS Independent
Classifier: Intended Audience :: Developers
Classifier: Intended Audience :: Science/Research
Classifier: Topic :: Scientific/Engineering :: Image Processing
Classifier: Topic :: Multimedia :: Graphics
Requires-Python: >=3.6
Requires-Dist: torch
Requires-Dist: torchvision
